langchain_robocorp/__init__.py
langchain_robocorp/_common.py
langchain_robocorp/_prompts.py
langchain_robocorp/py.typed
langchain_robocorp/toolkits.py
langchain_robocorp-0.0.10.post1.dist-info/LICENSE
langchain_robocorp-0.0.10.post1.dist-info/METADATA
langchain_robocorp-0.0.10.post1.dist-info/WHEEL
langchain_robocorp-0.0.10.post1.dist-info/RECORD
