Metadata-Version: 2.1
Name: langchain-robocorp
Version: 0.0.10.post1
Summary: An integration package connecting Robocorp Action Server and LangChain
Home-page: https://github.com/langchain-ai/langchain
License: MIT
Requires-Python: >=3.8.1,<4.0
Classifier: License :: OSI Approved :: MIT License
Classifier: Programming Language :: Python :: 3
Classifier: Programming Language :: Python :: 3.9
Classifier: Programming Language :: Python :: 3.10
Classifier: Programming Language :: Python :: 3.11
Classifier: Programming Language :: Python :: 3.12
Requires-Dist: langchain-core (>=0.2.24,<0.3)
Requires-Dist: requests (>=2.31.0,<3.0.0)
Requires-Dist: types-requests (>=2.31.0.6,<3.0.0.0)
Project-URL: Repository, https://github.com/langchain-ai/langchain
Project-URL: Source Code, https://github.com/langchain-ai/langchain/tree/v0.2/libs/partners/robocorp
